<?xml version="1.0" encoding="UTF-8"?>
<root>
   <element>
      <backlinks>&lt;div&gt;&lt;a href="https://www.rollingcrates.com/product-category/collapsible-crates/" target="_blank"&gt;foldable crate supplier&lt;/a&gt;,&lt;a href="https://www.rollingcrates.com/" target="_blank"&gt;moving stacking crate&lt;/a&gt;,&lt;a href="https://www.rollingcrates.com/product-category/distribution-containers/" target="_blank"&gt;storage bins with lids&lt;/a&gt;,&lt;a href="https://www.rollingcrates.com/product-category/industrial-plastic-boxes/" target="_blank"&gt;bale arm container&lt;/a&gt;,&lt;a href="https://www.rollingcrates.com/product-category/rolling-crates/" target="_blank"&gt;rolling storage crate with handle&lt;/a&gt;&lt;/div&gt;</backlinks>
      <category>rolling-crates</category>
      <commonproduct>5ef2e15248a9e4538ad193fc</commonproduct>
      <domain>5c51c7f7ec29c239e09d0972</domain>
      <dynamic_load />
      <external_height>440</external_height>
      <external_long>400</external_long>
      <external_width>360</external_width>
      <folded_height>85</folded_height>
      <generate_action_id>AtIVoWpPn</generate_action_id>
      <img_path>http://ali-us-west-1-products.oss-us-west-1.aliyuncs.com/products/d5d0e5e179ea4004ba8f09e18d23e2a3.JPG,http://ali-us-west-1-products.oss-us-west-1.aliyuncs.com/products/ca2865cb158248b9b85c635bcb5f2388.JPG,http://ali-us-west-1-products.oss-us-west-1.aliyuncs.com/products/fe75b7b937df40eb96db99afc05717dc.JPG,http://ali-us-west-1-products.oss-us-west-1.aliyuncs.com/products/6598368d9e6b481eb00a15c9121f1dee.JPG,http://ali-us-west-1-products.oss-us-west-1.aliyuncs.com/products/331a6d009f82467f8e5497ab2decdc41.JPG,http://ali-us-west-1-products.oss-us-west-1.aliyuncs.com/products/5cf290f4016b4cd5bc6d53ac9f80ab3b.JPG</img_path>
      <internal_height>440</internal_height>
      <internal_long>400</internal_long>
      <internal_width>360</internal_width>
      <model>64L Foldable shopping cart</model>
      <post_title>rolling crate</post_title>
      <post_title_slug>rolling-crate</post_title_slug>
      <product_identify_cat>rolling crate</product_identify_cat>
      <seo_meta_description>rolling crate, rolling plastic crate Wholesale, rolling crate supplier, high quality storage crate on wheels at wholesale prices, OEM &amp; ODM service</seo_meta_description>
      <seo_meta_facebook_description>rolling crate, rolling plastic crate Wholesale, rolling crate supplier, high quality storage crate on wheels at wholesale prices, OEM &amp; ODM service</seo_meta_facebook_description>
      <seo_meta_facebook_image />
      <seo_meta_facebook_title>rolling crate, rolling plastic crate Wholesale, rolling crate supplier</seo_meta_facebook_title>
      <seo_meta_seo_description>rolling crate, rolling plastic crate Wholesale, rolling crate supplier, high quality storage crate on wheels at wholesale prices, OEM &amp; ODM service</seo_meta_seo_description>
      <seo_meta_slug>rolling-crate-rolling-plastic-crate-wholesale-rolling-crate-supplier</seo_meta_slug>
      <seo_meta_title>rolling crate, rolling plastic crate Wholesale, rolling crate supplier</seo_meta_title>
      <seo_meta_twitter_description>rolling crate, rolling plastic crate Wholesale, rolling crate supplier, high quality storage crate on wheels at wholesale prices, OEM &amp; ODM service</seo_meta_twitter_description>
      <seo_meta_twitter_image />
      <seo_meta_twitter_title>rolling crate, rolling plastic crate Wholesale, rolling crate supplier</seo_meta_twitter_title>
      <static_load />
      <tags>foldable shopping carts,collapsible shopping trolley</tags>
      <volumn>64</volumn>
      <weight>3.9</weight>
   </element>
   <element>
      <backlinks>&lt;div&gt;&lt;a href="https://www.rollingcrates.com/product-category/collapsible-crates/" target="_blank"&gt;foldable crate&lt;/a&gt;,&lt;a href="https://www.rollingcrates.com/product-category/rolling-crates/" target="_blank"&gt;rolling storage crate&lt;/a&gt;,&lt;a href="https://www.rollingcrates.com/product-category/distribution-containers/" target="_blank"&gt;stackable distribution container&lt;/a&gt;,&lt;a href="https://www.rollingcrates.com/" target="_blank"&gt;plastic tote boxes&lt;/a&gt;,&lt;a href="https://www.rollingcrates.com/product-category/industrial-plastic-boxes/" target="_blank"&gt;stackable storage container set&lt;/a&gt;&lt;/div&gt;</backlinks>
      <category>rolling-crates</category>
      <commonproduct>5ef2e45748a9e4538ad19409</commonproduct>
      <domain>5c51c7f7ec29c239e09d0972</domain>
      <dynamic_load />
      <external_height>405</external_height>
      <external_long>420</external_long>
      <external_width>380</external_width>
      <folded_height>80</folded_height>
      <generate_action_id>AtIVoWpPn</generate_action_id>
      <img_path>http://ali-us-west-1-products.oss-us-west-1.aliyuncs.com/products/62f66e8a301a40dfaed93abe4721b96b.jpg,http://ali-us-west-1-products.oss-us-west-1.aliyuncs.com/products/ee4443c368b14ec39d10565ae7dce1f7.png,http://ali-us-west-1-products.oss-us-west-1.aliyuncs.com/products/d848514b7348400382dd68845a00b221.jpg,http://ali-us-west-1-products.oss-us-west-1.aliyuncs.com/products/29c86f4d208849d4a3ac3e8a085a8d00.jpg</img_path>
      <internal_height>405</internal_height>
      <internal_long>420</internal_long>
      <internal_width>380</internal_width>
      <model>64L collapsible shopping cart</model>
      <post_title>collapsible crate with wheels</post_title>
      <post_title_slug>collapsible-crate-with-wheels</post_title_slug>
      <product_identify_cat>rolling crate</product_identify_cat>
      <seo_meta_description>collapsible crate with wheels, rolling storage crate Wholesale, high quality rolling plastic crate at wholesale prices, OEM &amp; ODM service</seo_meta_description>
      <seo_meta_facebook_description>collapsible crate with wheels, rolling storage crate Wholesale, high quality rolling plastic crate at wholesale prices, OEM &amp; ODM service</seo_meta_facebook_description>
      <seo_meta_facebook_image />
      <seo_meta_facebook_title>collapsible crate with wheels, rolling storage crate Wholesale</seo_meta_facebook_title>
      <seo_meta_seo_description>collapsible crate with wheels, rolling storage crate Wholesale, high quality rolling plastic crate at wholesale prices, OEM &amp; ODM service</seo_meta_seo_description>
      <seo_meta_slug>collapsible-crate-with-wheels-rolling-storage-crate-wholesale</seo_meta_slug>
      <seo_meta_title>collapsible crate with wheels, rolling storage crate Wholesale</seo_meta_title>
      <seo_meta_twitter_description>collapsible crate with wheels, rolling storage crate Wholesale, high quality rolling plastic crate at wholesale prices, OEM &amp; ODM service</seo_meta_twitter_description>
      <seo_meta_twitter_image />
      <seo_meta_twitter_title>collapsible crate with wheels, rolling storage crate Wholesale</seo_meta_twitter_title>
      <static_load />
      <tags>foldable shopping carts,collapsible shopping trolley</tags>
      <volumn>64L</volumn>
      <weight>3</weight>
   </element>
</root>